nashopt.py
nashopt-1.0.0.dist-info/licenses/LICENSE
nashopt-1.0.0.dist-info/METADATA
nashopt-1.0.0.dist-info/WHEEL
nashopt-1.0.0.dist-info/top_level.txt
nashopt-1.0.0.dist-info/RECORD
