Metadata-Version: 2.4
Name: nashopt
Version: 1.0.0
Summary: NashOpt - A Python Library for Computing Generalized Nash Equilibria and Solving Game-Design and Game-Theoretic Control Problems.
Author-email: Alberto Bemporad <alberto.bemporad@imtlucca.it>
Project-URL: Homepage, https://github.com/bemporad/nashopt
Keywords: generalized nash equilibrium problems,game theory
Classifier: Programming Language :: Python :: 3
Classifier: License :: OSI Approved :: Apache Software License
Classifier: Operating System :: OS Independent
Requires-Python: >=3.9
License-File: LICENSE
Requires-Dist: numpy
Requires-Dist: jax
Requires-Dist: jaxopt
Requires-Dist: scipy
Requires-Dist: highspy
Requires-Dist: osqp
Dynamic: license-file
